pyshimmer/__init__.py
pyshimmer/serial_base.py
pyshimmer/test_util.py
pyshimmer/util.py
pyshimmer/bluetooth/__init__.py
pyshimmer/bluetooth/bt_api.py
pyshimmer/bluetooth/bt_commands.py
pyshimmer/bluetooth/bt_const.py
pyshimmer/bluetooth/bt_serial.py
pyshimmer/dev/__init__.py
pyshimmer/dev/base.py
pyshimmer/dev/calibration.py
pyshimmer/dev/channels.py
pyshimmer/dev/exg.py
pyshimmer/dev/fw_version.py
pyshimmer/reader/__init__.py
pyshimmer/reader/binary_reader.py
pyshimmer/reader/reader_const.py
pyshimmer/reader/shimmer_reader.py
pyshimmer/uart/__init__.py
pyshimmer/uart/dock_api.py
pyshimmer/uart/dock_const.py
pyshimmer/uart/dock_serial.py
pyshimmer-0.7.0.dist-info/LICENSE
pyshimmer-0.7.0.dist-info/METADATA
pyshimmer-0.7.0.dist-info/WHEEL
pyshimmer-0.7.0.dist-info/top_level.txt
pyshimmer-0.7.0.dist-info/RECORD
