Metadata-Version: 2.2
Name: pyshimmer
Version: 0.7.0
Summary: API for Shimmer sensor devices
Author: Lukas Magel
License:                     GNU GENERAL PUBLIC LICENSE
Project-URL: Homepage, https://github.com/seemoo-lab/pyshimmer
Keywords: shimmer,sensor,streaming
Classifier: License :: OSI Approved :: GNU General Public License v3 (GPLv3)
Classifier: Programming Language :: Python :: 3
Classifier: Development Status :: 4 - Beta
Requires-Python: >=3.7
License-File: LICENSE
Requires-Dist: pyserial>=3.4
Requires-Dist: numpy>=1.15
Requires-Dist: pandas>=1.1.5
Provides-Extra: test
Requires-Dist: pytest; extra == "test"
Requires-Dist: pytest-cov; extra == "test"
